sdo_image_parameter_api/__init__.py
sdo_image_parameter_api/image_methods.py
sdo_image_parameter_api/util/__init__.py
sdo_image_parameter_api/util/constants.py
sdo_image_parameter_api/util/converters.py
sdo_image_parameter_api/util/validators.py
sdo_image_parameter_api-0.1.0.dist-info/LICENSE
sdo_image_parameter_api-0.1.0.dist-info/METADATA
sdo_image_parameter_api-0.1.0.dist-info/WHEEL
sdo_image_parameter_api-0.1.0.dist-info/top_level.txt
sdo_image_parameter_api-0.1.0.dist-info/RECORD
