Metadata-Version: 2.1
Name: sdo-image-parameter-api
Version: 0.1.0
Summary: A toolkit for accessing solar image data
Home-page: https://bitbucket.org/ds4350-image-param-api-rm/solar-image-api/src/main/
Author: Ruqayyah Muse
Author-email: ruqayyahmuse@gmail.com
Maintainer: Ruqayyah Muse
Maintainer-email: ruqayyahmuse@gmail.com
License: MIT
Project-URL: Source, https://bitbucket.org/ds4350-image-param-api-rm/solar-image-api/src/main/
Project-URL: Web API, http://dmlab.cs.gsu.edu/dmlabapi/isd_docs.html
Keywords: sun,sdo,solar images,parameters
Classifier: License :: OSI Approved :: MIT License
Classifier: Programming Language :: Python :: 3
Classifier: Operating System :: OS Independent
License-File: LICENSE
Requires-Dist: numpy (==1.24.3)
Requires-Dist: Pillow (==9.5.0)
Requires-Dist: Requests (==2.29.0)
